MultiScraper/Aiohttp.py
MultiScraper/CloudScraper.py
MultiScraper/HttpClient.py
MultiScraper/LxmlSoup.py
MultiScraper/Regular.py
MultiScraper/Requests.py
MultiScraper/ResponseHandler.py
MultiScraper/Selenium.py
MultiScraper/Urllib.py
MultiScraper/__init__.py
MultiScraper/setup.py
MultiScraper-1.5.0.dist-info/LICENSE
MultiScraper-1.5.0.dist-info/METADATA
MultiScraper-1.5.0.dist-info/WHEEL
MultiScraper-1.5.0.dist-info/top_level.txt
MultiScraper-1.5.0.dist-info/RECORD
