Metadata-Version: 2.1
Name: MultiScraper
Version: 1.5.0
Summary: Multi Scraper is a set of tools for fast and easy parsing
Author: Alexander554
Author-email: gaa.280811@gamil.com
Keywords: MultiScraper
Classifier: Programming Language :: Python :: 3.11
Classifier: License :: OSI Approved :: MIT License
Classifier: Operating System :: OS Independent
Requires-Python: >=3.7
License-File: LICENSE
Requires-Dist: requests
Requires-Dist: lxml
Requires-Dist: bs4
Requires-Dist: aiohttp
Requires-Dist: cloudscraper
Requires-Dist: selenium
Requires-Dist: urllib3
Requires-Dist: cssselect
